whipweb/__about__.py
whipweb/__init__.py
whipweb/__main__.py
whipweb/app.py
whipweb/cli.py
whipweb/index.html
whipweb/settings.py
whipweb/static/obs_output_settings.png
whipweb/static/obs_stream_settings.png
whippyweb-1.0.0.dist-info/METADATA
whippyweb-1.0.0.dist-info/WHEEL
whippyweb-1.0.0.dist-info/entry_points.txt
whippyweb-1.0.0.dist-info/licenses/LICENSE
whippyweb-1.0.0.dist-info/RECORD
