Metadata-Version: 2.3
Name: WhipPyWeb
Version: 1.0.0
Summary: Add your description here
Project-URL: Issues, https://github.com/pkucmus/whipweb/issues
Project-URL: Source, https://github.com/pkucmus/whipweb
Author-email: Paweł Kucmus <pkucmus@gmail.com>
License: MIT License
License-File: LICENSE
Classifier: Development Status :: 3 - Alpha
Classifier: Intended Audience :: Developers
Classifier: License :: OSI Approved :: MIT License
Classifier: Operating System :: OS Independent
Classifier: Programming Language :: Python :: 3
Classifier: Topic :: Software Development :: Libraries :: Python Modules
Requires-Python: >=3.12
Requires-Dist: aiortc~=1.9.0
Requires-Dist: click~=8.1
Requires-Dist: rich~=13.8
Requires-Dist: starlette~=0.38
Requires-Dist: uvicorn~=0.30
Requires-Dist: websockets~=13.1
Provides-Extra: dev
Requires-Dist: ipdb; extra == 'dev'
Requires-Dist: ruff; extra == 'dev'
Provides-Extra: test
Requires-Dist: coverage[toml]; extra == 'test'
Requires-Dist: pytest-asyncio; extra == 'test'
Requires-Dist: pytest-cov; extra == 'test'
